aligned_treemap/__init__.py
aligned_treemap/treemap.py
aligned_treemap-1.0.5.dist-info/LICENSE.txt
aligned_treemap-1.0.5.dist-info/METADATA
aligned_treemap-1.0.5.dist-info/WHEEL
aligned_treemap-1.0.5.dist-info/top_level.txt
aligned_treemap-1.0.5.dist-info/RECORD
