Metadata-Version: 2.1
Name: aligned-treemap
Version: 1.0.5
Summary: Pure Python implementation of treemap, aligned_treemap, and squarify
Home-page: https://github.com/tony-tong-punchh/aligned_treemap
Author: Tony Tong, Uri Laserson
Author-email: ttong@pro-ai.org
License: Apache v2
Keywords: one-level treemap visualization layout graphics with ordered alignment along x and y axes
Platform: UNKNOWN
Classifier: Programming Language :: Python :: 3.5
Classifier: Programming Language :: Python :: 3.6
Classifier: Programming Language :: Python :: 3.7
Requires: numpy
